setup.py
GaussBinoDist/Binomialdistribution.py
GaussBinoDist/Gaussiandistribution.py
GaussBinoDist/Generaldistribution.py
GaussBinoDist/__init__.py
GaussBinoDist.egg-info/PKG-INFO
GaussBinoDist.egg-info/SOURCES.txt
GaussBinoDist.egg-info/dependency_links.txt
GaussBinoDist.egg-info/not-zip-safe
GaussBinoDist.egg-info/top_level.txt