Metadata-Version: 1.0
Name: GaussBinoDist
Version: 0.1
Summary: Gaussian distributions and Binomial distributions
Home-page: UNKNOWN
Author: Mohak Ashutosh Trivedi
Author-email: trivedimohak@gmail.com
License: UNKNOWN
Platform: UNKNOWN
